{
    "CreateTime": "2025-03-26 08:22:02",
    "CommitHash": "3ce38aeb501f78cc4f1b3d499b9bd5c875c91ba5",
    "PlatformMaster": {
        "AssetName": "OSX",
        "AssetSize": 1295,
        "AssetHash": "",
        "AssetCRC": 751299501,
        "ManifestName": "OSX.manifest",
        "ManifestSize": 931
    },
    "_keys": [
        "asset_bgm",
        "asset_enemy",
        "asset_jingle",
        "asset_navigator",
        "asset_scenes",
        "asset_se",
        "asset_signageui",
        "asset_timeline",
        "asset_virtual_field",
        "asset_voice"
    ],
    "_values": [
        {
            "AssetName": "asset_bgm",
            "AssetSize": 3521828,
            "AssetHash": "4eb8333f2ff4bf8006ecb54e72fb5aca",
            "AssetCRC": 3228635353,
            "ManifestName": "asset_bgm.manifest",
            "ManifestSize": 713
        },
        {
            "AssetName": "asset_enemy",
            "AssetSize": 1742878,
            "AssetHash": "068573a29ca415545d33050dcb8ecfe7",
            "AssetCRC": 1608917745,
            "ManifestName": "asset_enemy.manifest",
            "ManifestSize": 15817
        },
        {
            "AssetName": "asset_jingle",
            "AssetSize": 306783,
            "AssetHash": "49746c913f6d9b4cc51c62fcaaec16d4",
            "AssetCRC": 2562794278,
            "ManifestName": "asset_jingle.manifest",
            "ManifestSize": 520
        },
        {
            "AssetName": "asset_navigator",
            "AssetSize": 11480557,
            "AssetHash": "b204c36b3abdaf55b442cb018526bb7f",
            "AssetCRC": 3134036617,
            "ManifestName": "asset_navigator.manifest",
            "ManifestSize": 9653
        },
        {
            "AssetName": "asset_scenes",
            "AssetSize": 4839721,
            "AssetHash": "ea9e61f4323fd9212c06af15a030cc33",
            "AssetCRC": 1893564540,
            "ManifestName": "asset_scenes.manifest",
            "ManifestSize": 4258
        },
        {
            "AssetName": "asset_se",
            "AssetSize": 75042,
            "AssetHash": "18c182b3cefc42d91152f8e7c12f7d2b",
            "AssetCRC": 3703868663,
            "ManifestName": "asset_se.manifest",
            "ManifestSize": 649
        },
        {
            "AssetName": "asset_signageui",
            "AssetSize": 907899,
            "AssetHash": "3ba13ef831227017ff7d66951d034b22",
            "AssetCRC": 3498873058,
            "ManifestName": "asset_signageui.manifest",
            "ManifestSize": 1178
        },
        {
            "AssetName": "asset_timeline",
            "AssetSize": 16377,
            "AssetHash": "008cbcd9e9d54188bce25f3434b6204f",
            "AssetCRC": 2836914999,
            "ManifestName": "asset_timeline.manifest",
            "ManifestSize": 4439
        },
        {
            "AssetName": "asset_virtual_field",
            "AssetSize": 3346558,
            "AssetHash": "f7482d98851571a680c6a190384787f9",
            "AssetCRC": 3610651584,
            "ManifestName": "asset_virtual_field.manifest",
            "ManifestSize": 903
        },
        {
            "AssetName": "asset_voice",
            "AssetSize": 7600212,
            "AssetHash": "227eaded2b74319a497cf05720468b8c",
            "AssetCRC": 54743534,
            "ManifestName": "asset_voice.manifest",
            "ManifestSize": 2737
        }
    ]
}